ryzenaiyolov8m/__init__.py
ryzenaiyolov8m/anchors.npy
ryzenaiyolov8m/eval_onnx.py
ryzenaiyolov8m/general_json2yolo.py
ryzenaiyolov8m/infer_onnx.py
ryzenaiyolov8m/strides.npy
ryzenaiyolov8m/test_infer_onnx.py
ryzenaiyolov8m/utils.py
ryzenaiyolov8m-0.0.6.dist-info/METADATA
ryzenaiyolov8m-0.0.6.dist-info/WHEEL
ryzenaiyolov8m-0.0.6.dist-info/top_level.txt
ryzenaiyolov8m-0.0.6.dist-info/RECORD
