Metadata-Version: 2.1
Name: ryzenaiyolov8m
Version: 0.0.6
Summary: yolov8m for ryzenai test
Author: fangyuan
Author-email: fangyuan@amd.com
License: apache 3.0
